G4_PreprocessingLib/G4_PreprocessingLib.py
G4_PreprocessingLib/__init__.py
G4_PreprocessingLib-0.1.0.dist-info/LICENCE
G4_PreprocessingLib-0.1.0.dist-info/METADATA
G4_PreprocessingLib-0.1.0.dist-info/WHEEL
G4_PreprocessingLib-0.1.0.dist-info/top_level.txt
G4_PreprocessingLib-0.1.0.dist-info/RECORD
