Metadata-Version: 2.1
Name: G4_PreprocessingLib
Version: 0.1.0
Summary: Automatic preprocessing library for dataset cleaning
Author: Group 4: Aiora De La Lama, Katalin Garcia, Sofia Garlito, Maren Lakalle, Julen Pagola, Naia Sanz
Author-email: sofiamaria.garlito@mondragon.alumni.edu
Classifier: Programming Language :: Python :: 3
Classifier: License :: OSI Approved :: MIT License
Classifier: Operating System :: OS Independent
Requires-Python: >=3.6
License-File: LICENCE
Requires-Dist: pandas>=1.0.0
Requires-Dist: numpy>=1.18.0
Requires-Dist: scikit-learn>0.24.0
Requires-Dist: scipy>=1.0.0
